rerank/__init__.py
rerank/rankers/__init__.py
rerank/rankers/api_ranker.py
rerank/rankers/bm25.py
rerank/rankers/scaled_score_fusion.py
rerank/tools/__init__.py
rerank/tools/rerank_tool.py
rerank/tools/utils.py
rerank/utils/__init__.py
rerank/utils/callback.py
rerank/utils/constants.py
rerank/utils/ranker_connections.py
rerank/utils/ranker_parameters.py
rerank/utils/ranker_types.py
rerank/yamls/rerank_tool.yaml
tests/__init__.py
tests/test_rerank_tool.py
aml_promptflow_rerank-0.0.2.dist-info/METADATA
aml_promptflow_rerank-0.0.2.dist-info/WHEEL
aml_promptflow_rerank-0.0.2.dist-info/entry_points.txt
aml_promptflow_rerank-0.0.2.dist-info/top_level.txt
aml_promptflow_rerank-0.0.2.dist-info/RECORD
