Metadata-Version: 2.1
Name: aml-promptflow-rerank
Version: 0.0.2
Summary: This is my tools package
Requires-Dist: azure.ai.ml >=1.5.0
Requires-Dist: azure.identity >=1.12.0
Requires-Dist: azureml.rag[azure] !=0.2.31,>=0.2.28
Requires-Dist: requests >=2.28.1
Requires-Dist: requests-cache ~=1.1.1
Requires-Dist: ruamel.yaml <1.0.0,>=0.17.10
Requires-Dist: rank-bm25 <0.3,>=0.2.2
